Json2PascalVoc/Converter.py
Json2PascalVoc/__init__.py
Json2PascalVoc-1.0.5.dist-info/LICENSE
Json2PascalVoc-1.0.5.dist-info/METADATA
Json2PascalVoc-1.0.5.dist-info/WHEEL
Json2PascalVoc-1.0.5.dist-info/top_level.txt
Json2PascalVoc-1.0.5.dist-info/RECORD
