Metadata-Version: 2.1
Name: Json2PascalVoc
Version: 1.0.5
Summary: Package To Convert Json Files To PascalVOC XML files
Home-page: https://github.com/canerkaraguler/Json2PascalVOC
Author: Caner Karagüler
Author-email: caner.karaguler@gmail.com
License: UNKNOWN
Platform: UNKNOWN
Classifier: Programming Language :: Python :: 3
Classifier: License :: OSI Approved :: MIT License
Classifier: Operating System :: OS Independent
